{
  "dtkmc": "2023-2024学年第一学期期末",
  "ksid": "",
  "gjzsbfs": "OMR",
  "khws": 11,
  "khIdCode": 0,
  "khwsOptions": [
    0,
    1,
    2,
    3,
    4,
    5,
    6,
    7,
    8,
    9
  ],
  "ksmc": "",
  "kmmc": "普通答题卡",
  "dtkbs": "A32",
  "dtkzs": 1,
  "sideNumber": 2,
  "mfx": 0,
  "dtklx": 1,
  "omrStep": 1,
  "omrFloat": "top",
  "jsqWz": "everyone",
  "zysx": 1,
  "sjlx": 0,
  "sjlxOption": "A,B",
  "qk": 1,
  "wj": 1,
  "tzsl": 4,
  "tmsl": 22,
  "dtkmf": 0,
  "sjcc": [
    2480,
    1753
  ],
  "gsdy": [
    {
      "index": 1,
      "key": "1_A",
      "jsq": [
        {
          "index": 1,
          "location": [
            [
              110,
              90
            ],
            [
              1190,
              530
            ]
          ]
        }
      ],
      "qk": [
        {
          "index": 1,
          "location": [
            [
              214,
              474
            ],
            [
              241,
              495
            ]
          ]
        }
      ],
      "wj": [
        {
          "index": 1,
          "location": [
            [
              305,
              474
            ],
            [
              332,
              495
            ]
          ]
        }
      ],
      "omrKh": [
        {
          "index": 1,
          "positionArea": [
            {
              "index": "0",
              "location": [
                [
                  696,
                  230
                ],
                [
                  728,
                  249
                ]
              ]
            },
            {
              "index": "1",
              "location": [
                [
                  696,
                  256
                ],
                [
                  728,
                  275
                ]
              ]
            },
            {
              "index": "2",
              "location": [
                [
                  696,
                  282
                ],
                [
                  728,
                  301
                ]
              ]
            },
            {
              "index": "3",
              "location": [
                [
                  696,
                  308
                ],
                [
                  728,
                  327
                ]
              ]
            },
            {
              "index": "4",
              "location": [
                [
                  696,
                  334
                ],
                [
                  728,
                  353
                ]
              ]
            },
            {
              "index": "5",
              "location": [
                [
                  696,
                  360
                ],
                [
                  728,
                  379
                ]
              ]
            },
            {
              "index": "6",
              "location": [
                [
                  696,
                  386
                ],
                [
                  728,
                  405
                ]
              ]
            },
            {
              "index": "7",
              "location": [
                [
                  696,
                  412
                ],
                [
                  728,
                  431
                ]
              ]
            },
            {
              "index": "8",
              "location": [
                [
                  696,
                  438
                ],
                [
                  728,
                  457
                ]
              ]
            },
            {
              "index": "9",
              "location": [
                [
                  696,
                  464
                ],
                [
                  728,
                  483
                ]
              ]
            }
          ]
        },
        {
          "index": 2,
          "positionArea": [
            {
              "index": "0",
              "location": [
                [
                  742,
                  230
                ],
                [
                  774,
                  249
                ]
              ]
            },
            {
              "index": "1",
              "location": [
                [
                  742,
                  256
                ],
                [
                  774,
                  275
                ]
              ]
            },
            {
              "index": "2",
              "location": [
                [
                  742,
                  282
                ],
                [
                  774,
                  301
                ]
              ]
            },
            {
              "index": "3",
              "location": [
                [
                  742,
                  308
                ],
                [
                  774,
                  327
                ]
              ]
            },
            {
              "index": "4",
              "location": [
                [
                  742,
                  334
                ],
                [
                  774,
                  353
                ]
              ]
            },
            {
              "index": "5",
              "location": [
                [
                  742,
                  360
                ],
                [
                  774,
                  379
                ]
              ]
            },
            {
              "index": "6",
              "location": [
                [
                  742,
                  386
                ],
                [
                  774,
                  405
                ]
              ]
            },
            {
              "index": "7",
              "location": [
                [
                  742,
                  412
                ],
                [
                  774,
                  431
                ]
              ]
            },
            {
              "index": "8",
              "location": [
                [
                  742,
                  438
                ],
                [
                  774,
                  457
                ]
              ]
            },
            {
              "index": "9",
              "location": [
                [
                  742,
                  464
                ],
                [
                  774,
                  483
                ]
              ]
            }
          ]
        },
        {
          "index": 3,
          "positionArea": [
            {
              "index": "0",
              "location": [
                [
                  787,
                  230
                ],
                [
                  819,
                  249
                ]
              ]
            },
            {
              "index": "1",
              "location": [
                [
                  787,
                  256
                ],
                [
                  819,
                  275
                ]
              ]
            },
            {
              "index": "2",
              "location": [
                [
                  787,
                  282
                ],
                [
                  819,
                  301
                ]
              ]
            },
            {
              "index": "3",
              "location": [
                [
                  787,
                  308
                ],
                [
                  819,
                  327
                ]
              ]
            },
            {
              "index": "4",
              "location": [
                [
                  787,
                  334
                ],
                [
                  819,
                  353
                ]
              ]
            },
            {
              "index": "5",
              "location": [
                [
                  787,
                  360
                ],
                [
                  819,
                  379
                ]
              ]
            },
            {
              "index": "6",
              "location": [
                [
                  787,
                  386
                ],
                [
                  819,
                  405
                ]
              ]
            },
            {
              "index": "7",
              "location": [
                [
                  787,
                  412
                ],
                [
                  819,
                  431
                ]
              ]
            },
            {
              "index": "8",
              "location": [
                [
                  787,
                  438
                ],
                [
                  819,
                  457
                ]
              ]
            },
            {
              "index": "9",
              "location": [
                [
                  787,
                  464
                ],
                [
                  819,
                  483
                ]
              ]
            }
          ]
        },
        {
          "index": 4,
          "positionArea": [
            {
              "index": "0",
              "location": [
                [
                  832,
                  230
                ],
                [
                  864,
                  249
                ]
              ]
            },
            {
              "index": "1",
              "location": [
                [
                  832,
                  256
                ],
                [
                  864,
                  275
                ]
              ]
            },
            {
              "index": "2",
              "location": [
                [
                  832,
                  282
                ],
                [
                  864,
                  301
                ]
              ]
            },
            {
              "index": "3",
              "location": [
                [
                  832,
                  308
                ],
                [
                  864,
                  327
                ]
              ]
            },
            {
              "index": "4",
              "location": [
                [
                  832,
                  334
                ],
                [
                  864,
                  353
                ]
              ]
            },
            {
              "index": "5",
              "location": [
                [
                  832,
                  360
                ],
                [
                  864,
                  379
                ]
              ]
            },
            {
              "index": "6",
              "location": [
                [
                  832,
                  386
                ],
                [
                  864,
                  405
                ]
              ]
            },
            {
              "index": "7",
              "location": [
                [
                  832,
                  412
                ],
                [
                  864,
                  431
                ]
              ]
            },
            {
              "index": "8",
              "location": [
                [
                  832,
                  438
                ],
                [
                  864,
                  457
                ]
              ]
            },
            {
              "index": "9",
              "location": [
                [
                  832,
                  464
                ],
                [
                  864,
                  483
                ]
              ]
            }
          ]
        },
        {
          "index": 5,
          "positionArea": [
            {
              "index": "0",
              "location": [
                [
                  878,
                  230
                ],
                [
                  910,
                  249
                ]
              ]
            },
            {
              "index": "1",
              "location": [
                [
                  878,
                  256
                ],
                [
                  910,
                  275
                ]
              ]
            },
            {
              "index": "2",
              "location": [
                [
                  878,
                  282
                ],
                [
                  910,
                  301
                ]
              ]
            },
            {
              "index": "3",
              "location": [
                [
                  878,
                  308
                ],
                [
                  910,
                  327
                ]
              ]
            },
            {
              "index": "4",
              "location": [
                [
                  878,
                  334
                ],
                [
                  910,
                  353
                ]
              ]
            },
            {
              "index": "5",
              "location": [
                [
                  878,
                  360
                ],
                [
                  910,
                  379
                ]
              ]
            },
            {
              "index": "6",
              "location": [
                [
                  878,
                  386
                ],
                [
                  910,
                  405
                ]
              ]
            },
            {
              "index": "7",
              "location": [
                [
                  878,
                  412
                ],
                [
                  910,
                  431
                ]
              ]
            },
            {
              "index": "8",
              "location": [
                [
                  878,
                  438
                ],
                [
                  910,
                  457
                ]
              ]
            },
            {
              "index": "9",
              "location": [
                [
                  878,
                  464
                ],
                [
                  910,
                  483
                ]
              ]
            }
          ]
        },
        {
          "index": 6,
          "positionArea": [
            {
              "index": "0",
              "location": [
                [
                  923,
                  230
                ],
                [
                  955,
                  249
                ]
              ]
            },
            {
              "index": "1",
              "location": [
                [
                  923,
                  256
                ],
                [
                  955,
                  275
                ]
              ]
            },
            {
              "index": "2",
              "location": [
                [
                  923,
                  282
                ],
                [
                  955,
                  301
                ]
              ]
            },
            {
              "index": "3",
              "location": [
                [
                  923,
                  308
                ],
                [
                  955,
                  327
                ]
              ]
            },
            {
              "index": "4",
              "location": [
                [
                  923,
                  334
                ],
                [
                  955,
                  353
                ]
              ]
            },
            {
              "index": "5",
              "location": [
                [
                  923,
                  360
                ],
                [
                  955,
                  379
                ]
              ]
            },
            {
              "index": "6",
              "location": [
                [
                  923,
                  386
                ],
                [
                  955,
                  405
                ]
              ]
            },
            {
              "index": "7",
              "location": [
                [
                  923,
                  412
                ],
                [
                  955,
                  431
                ]
              ]
            },
            {
              "index": "8",
              "location": [
                [
                  923,
                  438
                ],
                [
                  955,
                  457
                ]
              ]
            },
            {
              "index": "9",
              "location": [
                [
                  923,
                  464
                ],
                [
                  955,
                  483
                ]
              ]
            }
          ]
        },
        {
          "index": 7,
          "positionArea": [
            {
              "index": "0",
              "location": [
                [
                  968,
                  230
                ],
                [
                  1000,
                  249
                ]
              ]
            },
            {
              "index": "1",
              "location": [
                [
                  968,
                  256
                ],
                [
                  1000,
                  275
                ]
              ]
            },
            {
              "index": "2",
              "location": [
                [
                  968,
                  282
                ],
                [
                  1000,
                  301
                ]
              ]
            },
            {
              "index": "3",
              "location": [
                [
                  968,
                  308
                ],
                [
                  1000,
                  327
                ]
              ]
            },
            {
              "index": "4",
              "location": [
                [
                  968,
                  334
                ],
                [
                  1000,
                  353
                ]
              ]
            },
            {
              "index": "5",
              "location": [
                [
                  968,
                  360
                ],
                [
                  1000,
                  379
                ]
              ]
            },
            {
              "index": "6",
              "location": [
                [
                  968,
                  386
                ],
                [
                  1000,
                  405
                ]
              ]
            },
            {
              "index": "7",
              "location": [
                [
                  968,
                  412
                ],
                [
                  1000,
                  431
                ]
              ]
            },
            {
              "index": "8",
              "location": [
                [
                  968,
                  438
                ],
                [
                  1000,
                  457
                ]
              ]
            },
            {
              "index": "9",
              "location": [
                [
                  968,
                  464
                ],
                [
                  1000,
                  483
                ]
              ]
            }
          ]
        },
        {
          "index": 8,
          "positionArea": [
            {
              "index": "0",
              "location": [
                [
                  1014,
                  230
                ],
                [
                  1046,
                  249
                ]
              ]
            },
            {
              "index": "1",
              "location": [
                [
                  1014,
                  256
                ],
                [
                  1046,
                  275
                ]
              ]
            },
            {
              "index": "2",
              "location": [
                [
                  1014,
                  282
                ],
                [
                  1046,
                  301
                ]
              ]
            },
            {
              "index": "3",
              "location": [
                [
                  1014,
                  308
                ],
                [
                  1046,
                  327
                ]
              ]
            },
            {
              "index": "4",
              "location": [
                [
                  1014,
                  334
                ],
                [
                  1046,
                  353
                ]
              ]
            },
            {
              "index": "5",
              "location": [
                [
                  1014,
                  360
                ],
                [
                  1046,
                  379
                ]
              ]
            },
            {
              "index": "6",
              "location": [
                [
                  1014,
                  386
                ],
                [
                  1046,
                  405
                ]
              ]
            },
            {
              "index": "7",
              "location": [
                [
                  1014,
                  412
                ],
                [
                  1046,
                  431
                ]
              ]
            },
            {
              "index": "8",
              "location": [
                [
                  1014,
                  438
                ],
                [
                  1046,
                  457
                ]
              ]
            },
            {
              "index": "9",
              "location": [
                [
                  1014,
                  464
                ],
                [
                  1046,
                  483
                ]
              ]
            }
          ]
        },
        {
          "index": 9,
          "positionArea": [
            {
              "index": "0",
              "location": [
                [
                  1059,
                  230
                ],
                [
                  1091,
                  249
                ]
              ]
            },
            {
              "index": "1",
              "location": [
                [
                  1059,
                  256
                ],
                [
                  1091,
                  275
                ]
              ]
            },
            {
              "index": "2",
              "location": [
                [
                  1059,
                  282
                ],
                [
                  1091,
                  301
                ]
              ]
            },
            {
              "index": "3",
              "location": [
                [
                  1059,
                  308
                ],
                [
                  1091,
                  327
                ]
              ]
            },
            {
              "index": "4",
              "location": [
                [
                  1059,
                  334
                ],
                [
                  1091,
                  353
                ]
              ]
            },
            {
              "index": "5",
              "location": [
                [
                  1059,
                  360
                ],
                [
                  1091,
                  379
                ]
              ]
            },
            {
              "index": "6",
              "location": [
                [
                  1059,
                  386
                ],
                [
                  1091,
                  405
                ]
              ]
            },
            {
              "index": "7",
              "location": [
                [
                  1059,
                  412
                ],
                [
                  1091,
                  431
                ]
              ]
            },
            {
              "index": "8",
              "location": [
                [
                  1059,
                  438
                ],
                [
                  1091,
                  457
                ]
              ]
            },
            {
              "index": "9",
              "location": [
                [
                  1059,
                  464
                ],
                [
                  1091,
                  483
                ]
              ]
            }
          ]
        },
        {
          "index": 10,
          "positionArea": [
            {
              "index": "0",
              "location": [
                [
                  1104,
                  230
                ],
                [
                  1136,
                  249
                ]
              ]
            },
            {
              "index": "1",
              "location": [
                [
                  1104,
                  256
                ],
                [
                  1136,
                  275
                ]
              ]
            },
            {
              "index": "2",
              "location": [
                [
                  1104,
                  282
                ],
                [
                  1136,
                  301
                ]
              ]
            },
            {
              "index": "3",
              "location": [
                [
                  1104,
                  308
                ],
                [
                  1136,
                  327
                ]
              ]
            },
            {
              "index": "4",
              "location": [
                [
                  1104,
                  334
                ],
                [
                  1136,
                  353
                ]
              ]
            },
            {
              "index": "5",
              "location": [
                [
                  1104,
                  360
                ],
                [
                  1136,
                  379
                ]
              ]
            },
            {
              "index": "6",
              "location": [
                [
                  1104,
                  386
                ],
                [
                  1136,
                  405
                ]
              ]
            },
            {
              "index": "7",
              "location": [
                [
                  1104,
                  412
                ],
                [
                  1136,
                  431
                ]
              ]
            },
            {
              "index": "8",
              "location": [
                [
                  1104,
                  438
                ],
                [
                  1136,
                  457
                ]
              ]
            },
            {
              "index": "9",
              "location": [
                [
                  1104,
                  464
                ],
                [
                  1136,
                  483
                ]
              ]
            }
          ]
        },
        {
          "index": 11,
          "positionArea": [
            {
              "index": "0",
              "location": [
                [
                  1150,
                  230
                ],
                [
                  1182,
                  249
                ]
              ]
            },
            {
              "index": "1",
              "location": [
                [
                  1150,
                  256
                ],
                [
                  1182,
                  275
                ]
              ]
            },
            {
              "index": "2",
              "location": [
                [
                  1150,
                  282
                ],
                [
                  1182,
                  301
                ]
              ]
            },
            {
              "index": "3",
              "location": [
                [
                  1150,
                  308
                ],
                [
                  1182,
                  327
                ]
              ]
            },
            {
              "index": "4",
              "location": [
                [
                  1150,
                  334
                ],
                [
                  1182,
                  353
                ]
              ]
            },
            {
              "index": "5",
              "location": [
                [
                  1150,
                  360
                ],
                [
                  1182,
                  379
                ]
              ]
            },
            {
              "index": "6",
              "location": [
                [
                  1150,
                  386
                ],
                [
                  1182,
                  405
                ]
              ]
            },
            {
              "index": "7",
              "location": [
                [
                  1150,
                  412
                ],
                [
                  1182,
                  431
                ]
              ]
            },
            {
              "index": "8",
              "location": [
                [
                  1150,
                  438
                ],
                [
                  1182,
                  457
                ]
              ]
            },
            {
              "index": "9",
              "location": [
                [
                  1150,
                  464
                ],
                [
                  1182,
                  483
                ]
              ]
            }
          ]
        }
      ],
      "ocrKh": [
        {
          "index": 1,
          "location": [
            [
              690,
              198
            ],
            [
              735,
              227
            ]
          ]
        },
        {
          "index": 2,
          "location": [
            [
              736,
              198
            ],
            [
              781,
              227
            ]
          ]
        },
        {
          "index": 3,
          "location": [
            [
              781,
              198
            ],
            [
              826,
              227
            ]
          ]
        },
        {
          "index": 4,
          "location": [
            [
              826,
              198
            ],
            [
              871,
              227
            ]
          ]
        },
        {
          "index": 5,
          "location": [
            [
              872,
              198
            ],
            [
              917,
              227
            ]
          ]
        },
        {
          "index": 6,
          "location": [
            [
              917,
              198
            ],
            [
              962,
              227
            ]
          ]
        },
        {
          "index": 7,
          "location": [
            [
              962,
              198
            ],
            [
              1007,
              227
            ]
          ]
        },
        {
          "index": 8,
          "location": [
            [
              1008,
              198
            ],
            [
              1053,
              227
            ]
          ]
        },
        {
          "index": 9,
          "location": [
            [
              1053,
              198
            ],
            [
              1098,
              227
            ]
          ]
        },
        {
          "index": 10,
          "location": [
            [
              1098,
              198
            ],
            [
              1143,
              227
            ]
          ]
        },
        {
          "index": 11,
          "location": [
            [
              1144,
              198
            ],
            [
              1189,
              227
            ]
          ]
        }
      ],
      "bjd": [
        {
          "index": 1,
          "location": [
            [
              70,
              50
            ],
            [
              90,
              70
            ]
          ],
          "iscy": 1
        },
        {
          "index": 2,
          "location": [
            [
              2390,
              50
            ],
            [
              2410,
              70
            ]
          ],
          "iscy": 0
        },
        {
          "index": 3,
          "location": [
            [
              2390,
              1683
            ],
            [
              2410,
              1703
            ]
          ],
          "iscy": 0
        },
        {
          "index": 4,
          "location": [
            [
              70,
              1683
            ],
            [
              90,
              1703
            ]
          ],
          "iscy": 0
        },
        {
          "index": 5,
          "location": [
            [
              110,
              50
            ],
            [
              124,
              70
            ]
          ],
          "iscy": 1
        }
      ],
      "qrcode": [
        {
          "index": 1,
          "location": [
            [
              1110,
              50
            ],
            [
              1190,
              130
            ]
          ]
        }
      ]
    },
    {
      "index": 2,
      "key": "1_B",
      "jsq": [],
      "bjd": [
        {
          "index": 1,
          "location": [
            [
              70,
              50
            ],
            [
              90,
              70
            ]
          ],
          "iscy": 1
        },
        {
          "index": 2,
          "location": [
            [
              2390,
              50
            ],
            [
              2410,
              70
            ]
          ],
          "iscy": 0
        },
        {
          "index": 3,
          "location": [
            [
              2390,
              1683
            ],
            [
              2410,
              1703
            ]
          ],
          "iscy": 0
        },
        {
          "index": 4,
          "location": [
            [
              70,
              1683
            ],
            [
              90,
              1703
            ]
          ],
          "iscy": 0
        },
        {
          "index": 5,
          "location": [
            [
              110,
              50
            ],
            [
              124,
              70
            ]
          ],
          "iscy": 1
        },
        {
          "index": 6,
          "location": [
            [
              132,
              50
            ],
            [
              146,
              70
            ]
          ],
          "iscy": 1
        }
      ],
      "qrcode": [
        {
          "index": 1,
          "location": [
            [
              0,
              0
            ],
            [
              0,
              0
            ]
          ]
        }
      ]
    }
  ],
  "jxxx": [
    {
      "tzmc": "选择题",
      "stlx": "1",
      "tzqz": "",
      "stxx": [
        {
          "stbh": 1,
          "stsx": 1,
          "stlx": 1,
          "stlxName": "单选题",
          "xzfw": [
            "A",
            "B",
            "C",
            "D"
          ],
          "stmf": 0,
          "bff": 0,
          "bzda": "",
          "tzqz": "",
          "position": [
            [
              167,
              589
            ],
            [
              351,
              606
            ]
          ],
          "isChoose": 0,
          "positionArea": [
            {
              "index": "A",
              "location": [
                [
                  167,
                  589
                ],
                [
                  199,
                  605
                ]
              ],
              "paper": "1_A",
              "paperIndex": "1"
            },
            {
              "index": "B",
              "location": [
                [
                  213,
                  589
                ],
                [
                  245,
                  605
                ]
              ],
              "paper": "1_A",
              "paperIndex": "1"
            },
            {
              "index": "C",
              "location": [
                [
                  259,
                  589
                ],
                [
                  291,
                  605
                ]
              ],
              "paper": "1_A",
              "paperIndex": "1"
            },
            {
              "index": "D",
              "location": [
                [
                  305,
                  589
                ],
                [
                  337,
                  605
                ]
              ],
              "paper": "1_A",
              "paperIndex": "1"
            }
          ],
          "show_zdy": false,
          "id": "1719962062265950208",
          "stmc": "1",
          "paper": "1_A",
          "paperIndex": "1"
        },
        {
          "stbh": 2,
          "stsx": 2,
          "stlx": 1,
          "stlxName": "单选题",
          "xzfw": [
            "A",
            "B",
            "C",
            "D"
          ],
          "stmf": 0,
          "bff": 0,
          "bzda": "",
          "tzqz": "",
          "position": [
            [
              167,
              612
            ],
            [
              351,
              629
            ]
          ],
          "isChoose": 0,
          "positionArea": [
            {
              "index": "A",
              "location": [
                [
                  167,
                  612
                ],
                [
                  199,
                  628
                ]
              ],
              "paper": "1_A",
              "paperIndex": "1"
            },
            {
              "index": "B",
              "location": [
                [
                  213,
                  612
                ],
                [
                  245,
                  628
                ]
              ],
              "paper": "1_A",
              "paperIndex": "1"
            },
            {
              "index": "C",
              "location": [
                [
                  259,
                  612
                ],
                [
                  291,
                  628
                ]
              ],
              "paper": "1_A",
              "paperIndex": "1"
            },
            {
              "index": "D",
              "location": [
                [
                  305,
                  612
                ],
                [
                  337,
                  628
                ]
              ],
              "paper": "1_A",
              "paperIndex": "1"
            }
          ],
          "show_zdy": false,
          "id": "1719962062265950209",
          "stmc": "2",
          "paper": "1_A",
          "paperIndex": "1"
        },
        {
          "stbh": 3,
          "stsx": 3,
          "stlx": 1,
          "stlxName": "单选题",
          "xzfw": [
            "A",
            "B",
            "C",
            "D"
          ],
          "stmf": 0,
          "bff": 0,
          "bzda": "",
          "tzqz": "",
          "position": [
            [
              167,
              635
            ],
            [
              351,
              652
            ]
          ],
          "isChoose": 0,
          "positionArea": [
            {
              "index": "A",
              "location": [
                [
                  167,
                  635
                ],
                [
                  199,
                  651
                ]
              ],
              "paper": "1_A",
              "paperIndex": "1"
            },
            {
              "index": "B",
              "location": [
                [
                  213,
                  635
                ],
                [
                  245,
                  651
                ]
              ],
              "paper": "1_A",
              "paperIndex": "1"
            },
            {
              "index": "C",
              "location": [
                [
                  259,
                  635
                ],
                [
                  291,
                  651
                ]
              ],
              "paper": "1_A",
              "paperIndex": "1"
            },
            {
              "index": "D",
              "location": [
                [
                  305,
                  635
                ],
                [
                  337,
                  651
                ]
              ],
              "paper": "1_A",
              "paperIndex": "1"
            }
          ],
          "show_zdy": false,
          "id": "1719962062265950210",
          "stmc": "3",
          "paper": "1_A",
          "paperIndex": "1"
        },
        {
          "stbh": 4,
          "stsx": 4,
          "stlx": 1,
          "stlxName": "单选题",
          "xzfw": [
            "A",
            "B",
            "C",
            "D"
          ],
          "stmf": 0,
          "bff": 0,
          "bzda": "",
          "tzqz": "",
          "position": [
            [
              167,
              657
            ],
            [
              351,
              674
            ]
          ],
          "isChoose": 0,
          "positionArea": [
            {
              "index": "A",
              "location": [
                [
                  167,
                  657
                ],
                [
                  199,
                  673
                ]
              ],
              "paper": "1_A",
              "paperIndex": "1"
            },
            {
              "index": "B",
              "location": [
                [
                  213,
                  657
                ],
                [
                  245,
                  673
                ]
              ],
              "paper": "1_A",
              "paperIndex": "1"
            },
            {
              "index": "C",
              "location": [
                [
                  259,
                  657
                ],
                [
                  291,
                  673
                ]
              ],
              "paper": "1_A",
              "paperIndex": "1"
            },
            {
              "index": "D",
              "location": [
                [
                  305,
                  657
                ],
                [
                  337,
                  673
                ]
              ],
              "paper": "1_A",
              "paperIndex": "1"
            }
          ],
          "show_zdy": false,
          "id": "1719962062265950211",
          "stmc": "4",
          "paper": "1_A",
          "paperIndex": "1"
        },
        {
          "stbh": 5,
          "stsx": 5,
          "stlx": 1,
          "stlxName": "单选题",
          "xzfw": [
            "A",
            "B",
            "C",
            "D"
          ],
          "stmf": 0,
          "bff": 0,
          "bzda": "",
          "tzqz": "",
          "position": [
            [
              167,
              680
            ],
            [
              351,
              697
            ]
          ],
          "isChoose": 0,
          "positionArea": [
            {
              "index": "A",
              "location": [
                [
                  167,
                  680
                ],
                [
                  199,
                  696
                ]
              ],
              "paper": "1_A",
              "paperIndex": "1"
            },
            {
              "index": "B",
              "location": [
                [
                  213,
                  680
                ],
                [
                  245,
                  696
                ]
              ],
              "paper": "1_A",
              "paperIndex": "1"
            },
            {
              "index": "C",
              "location": [
                [
                  259,
                  680
                ],
                [
                  291,
                  696
                ]
              ],
              "paper": "1_A",
              "paperIndex": "1"
            },
            {
              "index": "D",
              "location": [
                [
                  305,
                  680
                ],
                [
                  337,
                  696
                ]
              ],
              "paper": "1_A",
              "paperIndex": "1"
            }
          ],
          "show_zdy": false,
          "id": "1719962062265950212",
          "stmc": "5",
          "paper": "1_A",
          "paperIndex": "1"
        },
        {
          "stbh": 6,
          "stsx": 6,
          "stlx": 1,
          "stlxName": "单选题",
          "xzfw": [
            "A",
            "B",
            "C",
            "D"
          ],
          "stmf": 0,
          "bff": 0,
          "bzda": "",
          "tzqz": "",
          "position": [
            [
              408,
              589
            ],
            [
              592,
              606
            ]
          ],
          "isChoose": 0,
          "positionArea": [
            {
              "index": "A",
              "location": [
                [
                  408,
                  589
                ],
                [
                  440,
                  605
                ]
              ],
              "paper": "1_A",
              "paperIndex": "1"
            },
            {
              "index": "B",
              "location": [
                [
                  454,
                  589
                ],
                [
                  486,
                  605
                ]
              ],
              "paper": "1_A",
              "paperIndex": "1"
            },
            {
              "index": "C",
              "location": [
                [
                  500,
                  589
                ],
                [
                  532,
                  605
                ]
              ],
              "paper": "1_A",
              "paperIndex": "1"
            },
            {
              "index": "D",
              "location": [
                [
                  546,
                  589
                ],
                [
                  578,
                  605
                ]
              ],
              "paper": "1_A",
              "paperIndex": "1"
            }
          ],
          "show_zdy": false,
          "id": "1719962062265950213",
          "stmc": "6",
          "paper": "1_A",
          "paperIndex": "1"
        },
        {
          "stbh": 7,
          "stsx": 7,
          "stlx": 1,
          "stlxName": "单选题",
          "xzfw": [
            "A",
            "B",
            "C",
            "D"
          ],
          "stmf": 0,
          "bff": 0,
          "bzda": "",
          "tzqz": "",
          "position": [
            [
              408,
              612
            ],
            [
              592,
              629
            ]
          ],
          "isChoose": 0,
          "positionArea": [
            {
              "index": "A",
              "location": [
                [
                  408,
                  612
                ],
                [
                  440,
                  628
                ]
              ],
              "paper": "1_A",
              "paperIndex": "1"
            },
            {
              "index": "B",
              "location": [
                [
                  454,
                  612
                ],
                [
                  486,
                  628
                ]
              ],
              "paper": "1_A",
              "paperIndex": "1"
            },
            {
              "index": "C",
              "location": [
                [
                  500,
                  612
                ],
                [
                  532,
                  628
                ]
              ],
              "paper": "1_A",
              "paperIndex": "1"
            },
            {
              "index": "D",
              "location": [
                [
                  546,
                  612
                ],
                [
                  578,
                  628
                ]
              ],
              "paper": "1_A",
              "paperIndex": "1"
            }
          ],
          "show_zdy": false,
          "id": "1719962062265950214",
          "stmc": "7",
          "paper": "1_A",
          "paperIndex": "1"
        },
        {
          "stbh": 8,
          "stsx": 8,
          "stlx": 1,
          "stlxName": "单选题",
          "xzfw": [
            "A",
            "B",
            "C",
            "D"
          ],
          "stmf": 0,
          "bff": 0,
          "bzda": "",
          "tzqz": "",
          "position": [
            [
              408,
              635
            ],
            [
              592,
              652
            ]
          ],
          "isChoose": 0,
          "positionArea": [
            {
              "index": "A",
              "location": [
                [
                  408,
                  635
                ],
                [
                  440,
                  651
                ]
              ],
              "paper": "1_A",
              "paperIndex": "1"
            },
            {
              "index": "B",
              "location": [
                [
                  454,
                  635
                ],
                [
                  486,
                  651
                ]
              ],
              "paper": "1_A",
              "paperIndex": "1"
            },
            {
              "index": "C",
              "location": [
                [
                  500,
                  635
                ],
                [
                  532,
                  651
                ]
              ],
              "paper": "1_A",
              "paperIndex": "1"
            },
            {
              "index": "D",
              "location": [
                [
                  546,
                  635
                ],
                [
                  578,
                  651
                ]
              ],
              "paper": "1_A",
              "paperIndex": "1"
            }
          ],
          "show_zdy": false,
          "id": "1719962062265950215",
          "stmc": "8",
          "paper": "1_A",
          "paperIndex": "1"
        },
        {
          "stbh": 9,
          "stsx": 9,
          "stlx": 1,
          "stlxName": "单选题",
          "xzfw": [
            "A",
            "B",
            "C",
            "D"
          ],
          "stmf": 0,
          "bff": 0,
          "bzda": "",
          "tzqz": "",
          "position": [
            [
              408,
              657
            ],
            [
              592,
              674
            ]
          ],
          "isChoose": 0,
          "positionArea": [
            {
              "index": "A",
              "location": [
                [
                  408,
                  657
                ],
                [
                  440,
                  673
                ]
              ],
              "paper": "1_A",
              "paperIndex": "1"
            },
            {
              "index": "B",
              "location": [
                [
                  454,
                  657
                ],
                [
                  486,
                  673
                ]
              ],
              "paper": "1_A",
              "paperIndex": "1"
            },
            {
              "index": "C",
              "location": [
                [
                  500,
                  657
                ],
                [
                  532,
                  673
                ]
              ],
              "paper": "1_A",
              "paperIndex": "1"
            },
            {
              "index": "D",
              "location": [
                [
                  546,
                  657
                ],
                [
                  578,
                  673
                ]
              ],
              "paper": "1_A",
              "paperIndex": "1"
            }
          ],
          "show_zdy": false,
          "id": "1719962062265950216",
          "stmc": "9",
          "paper": "1_A",
          "paperIndex": "1"
        },
        {
          "stbh": 10,
          "stsx": 10,
          "stlx": 1,
          "stlxName": "单选题",
          "xzfw": [
            "A",
            "B",
            "C",
            "D"
          ],
          "stmf": 0,
          "bff": 0,
          "bzda": "",
          "tzqz": "",
          "position": [
            [
              408,
              680
            ],
            [
              592,
              697
            ]
          ],
          "isChoose": 0,
          "positionArea": [
            {
              "index": "A",
              "location": [
                [
                  408,
                  680
                ],
                [
                  440,
                  696
                ]
              ],
              "paper": "1_A",
              "paperIndex": "1"
            },
            {
              "index": "B",
              "location": [
                [
                  454,
                  680
                ],
                [
                  486,
                  696
                ]
              ],
              "paper": "1_A",
              "paperIndex": "1"
            },
            {
              "index": "C",
              "location": [
                [
                  500,
                  680
                ],
                [
                  532,
                  696
                ]
              ],
              "paper": "1_A",
              "paperIndex": "1"
            },
            {
              "index": "D",
              "location": [
                [
                  546,
                  680
                ],
                [
                  578,
                  696
                ]
              ],
              "paper": "1_A",
              "paperIndex": "1"
            }
          ],
          "show_zdy": false,
          "id": "1719962062265950217",
          "stmc": "10",
          "paper": "1_A",
          "paperIndex": "1"
        }
      ],
      "id": 1,
      "tzmf": 0,
      "tmsl": 10,
      "answer": true
    },
    {
      "tzmc": "选择题",
      "stlx": 1,
      "tzqz": "",
      "stxx": [
        {
          "stbh": 11,
          "stsx": 11,
          "stlx": 2,
          "stlxName": "多选题",
          "xzfw": [
            "A",
            "B",
            "C",
            "D"
          ],
          "stmf": 0,
          "bff": 0,
          "bzda": "",
          "tzqz": "",
          "position": [
            [
              167,
              772
            ],
            [
              351,
              789
            ]
          ],
          "isChoose": 0,
          "positionArea": [
            {
              "index": "A",
              "location": [
                [
                  167,
                  772
                ],
                [
                  199,
                  788
                ]
              ],
              "paper": "1_A",
              "paperIndex": "1"
            },
            {
              "index": "B",
              "location": [
                [
                  213,
                  772
                ],
                [
                  245,
                  788
                ]
              ],
              "paper": "1_A",
              "paperIndex": "1"
            },
            {
              "index": "C",
              "location": [
                [
                  259,
                  772
                ],
                [
                  291,
                  788
                ]
              ],
              "paper": "1_A",
              "paperIndex": "1"
            },
            {
              "index": "D",
              "location": [
                [
                  305,
                  772
                ],
                [
                  337,
                  788
                ]
              ],
              "paper": "1_A",
              "paperIndex": "1"
            }
          ],
          "show_zdy": false,
          "id": "1719962100744495104",
          "stmc": "11",
          "paper": "1_A",
          "paperIndex": "1"
        },
        {
          "stbh": 12,
          "stsx": 12,
          "stlx": 2,
          "stlxName": "多选题",
          "xzfw": [
            "A",
            "B",
            "C",
            "D"
          ],
          "stmf": 0,
          "bff": 0,
          "bzda": "",
          "tzqz": "",
          "position": [
            [
              167,
              795
            ],
            [
              351,
              812
            ]
          ],
          "isChoose": 0,
          "positionArea": [
            {
              "index": "A",
              "location": [
                [
                  167,
                  795
                ],
                [
                  199,
                  811
                ]
              ],
              "paper": "1_A",
              "paperIndex": "1"
            },
            {
              "index": "B",
              "location": [
                [
                  213,
                  795
                ],
                [
                  245,
                  811
                ]
              ],
              "paper": "1_A",
              "paperIndex": "1"
            },
            {
              "index": "C",
              "location": [
                [
                  259,
                  795
                ],
                [
                  291,
                  811
                ]
              ],
              "paper": "1_A",
              "paperIndex": "1"
            },
            {
              "index": "D",
              "location": [
                [
                  305,
                  795
                ],
                [
                  337,
                  811
                ]
              ],
              "paper": "1_A",
              "paperIndex": "1"
            }
          ],
          "show_zdy": false,
          "id": "1719962100748689408",
          "stmc": "12",
          "paper": "1_A",
          "paperIndex": "1"
        },
        {
          "stbh": 13,
          "stsx": 13,
          "stlx": 2,
          "stlxName": "多选题",
          "xzfw": [
            "A",
            "B",
            "C",
            "D"
          ],
          "stmf": 0,
          "bff": 0,
          "bzda": "",
          "tzqz": "",
          "position": [
            [
              167,
              818
            ],
            [
              351,
              835
            ]
          ],
          "isChoose": 0,
          "positionArea": [
            {
              "index": "A",
              "location": [
                [
                  167,
                  818
                ],
                [
                  199,
                  834
                ]
              ],
              "paper": "1_A",
              "paperIndex": "1"
            },
            {
              "index": "B",
              "location": [
                [
                  213,
                  818
                ],
                [
                  245,
                  834
                ]
              ],
              "paper": "1_A",
              "paperIndex": "1"
            },
            {
              "index": "C",
              "location": [
                [
                  259,
                  818
                ],
                [
                  291,
                  834
                ]
              ],
              "paper": "1_A",
              "paperIndex": "1"
            },
            {
              "index": "D",
              "location": [
                [
                  305,
                  818
                ],
                [
                  337,
                  834
                ]
              ],
              "paper": "1_A",
              "paperIndex": "1"
            }
          ],
          "show_zdy": false,
          "id": "1719962100748689409",
          "stmc": "13",
          "paper": "1_A",
          "paperIndex": "1"
        },
        {
          "stbh": 14,
          "stsx": 14,
          "stlx": 2,
          "stlxName": "多选题",
          "xzfw": [
            "A",
            "B",
            "C",
            "D"
          ],
          "stmf": 0,
          "bff": 0,
          "bzda": "",
          "tzqz": "",
          "position": [
            [
              167,
              840
            ],
            [
              351,
              857
            ]
          ],
          "isChoose": 0,
          "positionArea": [
            {
              "index": "A",
              "location": [
                [
                  167,
                  840
                ],
                [
                  199,
                  856
                ]
              ],
              "paper": "1_A",
              "paperIndex": "1"
            },
            {
              "index": "B",
              "location": [
                [
                  213,
                  840
                ],
                [
                  245,
                  856
                ]
              ],
              "paper": "1_A",
              "paperIndex": "1"
            },
            {
              "index": "C",
              "location": [
                [
                  259,
                  840
                ],
                [
                  291,
                  856
                ]
              ],
              "paper": "1_A",
              "paperIndex": "1"
            },
            {
              "index": "D",
              "location": [
                [
                  305,
                  840
                ],
                [
                  337,
                  856
                ]
              ],
              "paper": "1_A",
              "paperIndex": "1"
            }
          ],
          "show_zdy": false,
          "id": "1719962100748689410",
          "stmc": "14",
          "paper": "1_A",
          "paperIndex": "1"
        },
        {
          "stbh": 15,
          "stsx": 15,
          "stlx": 2,
          "stlxName": "多选题",
          "xzfw": [
            "A",
            "B",
            "C",
            "D"
          ],
          "stmf": 0,
          "bff": 0,
          "bzda": "",
          "tzqz": "",
          "position": [
            [
              167,
              863
            ],
            [
              351,
              880
            ]
          ],
          "isChoose": 0,
          "positionArea": [
            {
              "index": "A",
              "location": [
                [
                  167,
                  863
                ],
                [
                  199,
                  879
                ]
              ],
              "paper": "1_A",
              "paperIndex": "1"
            },
            {
              "index": "B",
              "location": [
                [
                  213,
                  863
                ],
                [
                  245,
                  879
                ]
              ],
              "paper": "1_A",
              "paperIndex": "1"
            },
            {
              "index": "C",
              "location": [
                [
                  259,
                  863
                ],
                [
                  291,
                  879
                ]
              ],
              "paper": "1_A",
              "paperIndex": "1"
            },
            {
              "index": "D",
              "location": [
                [
                  305,
                  863
                ],
                [
                  337,
                  879
                ]
              ],
              "paper": "1_A",
              "paperIndex": "1"
            }
          ],
          "show_zdy": false,
          "id": "1719962100748689411",
          "stmc": "15",
          "paper": "1_A",
          "paperIndex": "1"
        }
      ],
      "id": 2,
      "tzmf": 0,
      "tmsl": 5,
      "answer": true
    },
    {
      "tzmc": "填空题",
      "stlx": "4",
      "tzqz": "",
      "stxx": [
        {
          "stbh": 4000,
          "stsx": 16,
          "stlx": 4,
          "stlxName": "填空题",
          "xzfw": [],
          "stmf": 0,
          "bff": 0,
          "bzda": [
            ""
          ],
          "tzqz": "",
          "position": [
            [
              110,
              941
            ],
            [
              1190,
              1059
            ]
          ],
          "isChoose": 0,
          "positionArea": [
            {
              "index": 1,
              "location": [
                [
                  123,
                  959
                ],
                [
                  399,
                  995
                ]
              ],
              "paper": "1_A",
              "paperIndex": "1"
            }
          ],
          "show_zdy": false,
          "id": "1719962118377349120",
          "stmc": "16",
          "paper": "1_A",
          "paperIndex": "1"
        },
        {
          "stbh": 4001,
          "stsx": 17,
          "stlx": 4,
          "stlxName": "填空题",
          "xzfw": [],
          "stmf": 0,
          "bff": 0,
          "bzda": [
            ""
          ],
          "tzqz": "",
          "position": [
            [
              110,
              941
            ],
            [
              1190,
              1059
            ]
          ],
          "isChoose": 0,
          "positionArea": [
            {
              "index": 1,
              "location": [
                [
                  412,
                  959
                ],
                [
                  688,
                  995
                ]
              ],
              "paper": "1_A",
              "paperIndex": "1"
            }
          ],
          "show_zdy": false,
          "id": "1719962118377349121",
          "stmc": "17",
          "paper": "1_A",
          "paperIndex": "1"
        },
        {
          "stbh": 4002,
          "stsx": 18,
          "stlx": 4,
          "stlxName": "填空题",
          "xzfw": [],
          "stmf": 0,
          "bff": 0,
          "bzda": [
            ""
          ],
          "tzqz": "",
          "position": [
            [
              110,
              941
            ],
            [
              1190,
              1059
            ]
          ],
          "isChoose": 0,
          "positionArea": [
            {
              "index": 1,
              "location": [
                [
                  701,
                  959
                ],
                [
                  977,
                  995
                ]
              ],
              "paper": "1_A",
              "paperIndex": "1"
            }
          ],
          "show_zdy": false,
          "id": "1719962118377349122",
          "stmc": "18",
          "paper": "1_A",
          "paperIndex": "1"
        },
        {
          "stbh": 4003,
          "stsx": 19,
          "stlx": 4,
          "stlxName": "填空题",
          "xzfw": [],
          "stmf": 0,
          "bff": 0,
          "bzda": [
            ""
          ],
          "tzqz": "",
          "position": [
            [
              110,
              941
            ],
            [
              1190,
              1059
            ]
          ],
          "isChoose": 0,
          "positionArea": [
            {
              "index": 1,
              "location": [
                [
                  123,
                  1013
                ],
                [
                  399,
                  1049
                ]
              ],
              "paper": "1_A",
              "paperIndex": "1"
            }
          ],
          "show_zdy": false,
          "id": "1719962118377349123",
          "stmc": "19",
          "paper": "1_A",
          "paperIndex": "1"
        }
      ],
      "id": 3,
      "tzmf": 0,
      "tmsl": 4
    },
    {
      "tzmc": "主观题",
      "stlx": "5",
      "tzqz": "",
      "stxx": [
        {
          "stbh": 5000,
          "stsx": 20,
          "stlx": 5,
          "stlxName": "简答题",
          "xzfw": [],
          "stmf": 0,
          "bff": 0,
          "bzda": "",
          "tzqz": "",
          "position": [
            [
              110,
              1105
            ],
            [
              1192,
              1671
            ]
          ],
          "isChoose": 0,
          "positionArea": [
            {
              "index": 1,
              "location": [
                [
                  110,
                  1105
                ],
                [
                  1192,
                  1671
                ]
              ],
              "paper": "1_A",
              "paperIndex": "1"
            }
          ],
          "show_zdy": false,
          "id": "1719962136349941760",
          "stmc": "20",
          "paper": "1_A",
          "paperIndex": "1"
        },
        {
          "stbh": 5001,
          "stsx": 21,
          "stlx": 5,
          "stlxName": "简答题",
          "xzfw": [],
          "stmf": 0,
          "bff": 0,
          "bzda": "",
          "tzqz": "",
          "position": [
            [
              1255,
              90
            ],
            [
              2337,
              1664
            ]
          ],
          "isChoose": 0,
          "positionArea": [
            {
              "index": 1,
              "location": [
                [
                  1255,
                  90
                ],
                [
                  2337,
                  1664
                ]
              ],
              "paper": "1_A",
              "paperIndex": "1"
            }
          ],
          "show_zdy": false,
          "id": "1719962136349941761",
          "stmc": "21",
          "paper": "1_A",
          "paperIndex": "1"
        },
        {
          "stbh": 5002,
          "stsx": 22,
          "stlx": 5,
          "stlxName": "简答题",
          "xzfw": [],
          "stmf": 0,
          "bff": 0,
          "bzda": "",
          "tzqz": "",
          "position": [
            [
              110,
              90
            ],
            [
              1192,
              1654
            ]
          ],
          "isChoose": 0,
          "positionArea": [
            {
              "index": 1,
              "location": [
                [
                  110,
                  90
                ],
                [
                  1192,
                  1654
                ]
              ],
              "paper": "1_B",
              "paperIndex": "2"
            }
          ],
          "show_zdy": false,
          "id": "1719962136354136064",
          "stmc": "22",
          "paper": "1_B",
          "paperIndex": "2"
        }
      ],
      "id": 4,
      "chooseNumber": 0,
      "chooseNumberTotle": 0,
      "type": "df",
      "tzmf": 0,
      "tmsl": 3
    }
  ],
  "choiceQuestionOpt": {},
  "_ty": ""
}